updog/__init__.py
updog/__main__.py
updog/static/css/bootstrap.min.css
updog/static/css/font.scss
updog/static/css/style.min.css
updog/static/css/style.scss
updog/static/fonts/poppins/poppins-v5-latin-300.eot
updog/static/fonts/poppins/poppins-v5-latin-300.svg
updog/static/fonts/poppins/poppins-v5-latin-300.ttf
updog/static/fonts/poppins/poppins-v5-latin-300.woff
updog/static/fonts/poppins/poppins-v5-latin-300.woff2
updog/static/fonts/poppins/poppins-v5-latin-600.eot
updog/static/fonts/poppins/poppins-v5-latin-600.svg
updog/static/fonts/poppins/poppins-v5-latin-600.ttf
updog/static/fonts/poppins/poppins-v5-latin-600.woff
updog/static/fonts/poppins/poppins-v5-latin-600.woff2
updog/static/images/favicon.ico
updog/static/images/updog.png
updog/static/js/bootstrap.bundle.min.js
updog/static/js/jquery-3.7.1.min.js
updog/static/js/main.js
updog/static/vendor/datatable/DataTables-1.10.18/images/sort_asc.png
updog/static/vendor/datatable/DataTables-1.10.18/images/sort_asc_disabled.png
updog/static/vendor/datatable/DataTables-1.10.18/images/sort_both.png
updog/static/vendor/datatable/DataTables-1.10.18/images/sort_desc.png
updog/static/vendor/datatable/DataTables-1.10.18/images/sort_desc_disabled.png
updog/static/vendor/datatable/datatables.min.css
updog/static/vendor/datatable/datatables.min.js
updog/static/vendor/datatable/file-size.js
updog/static/vendor/fontawesome-5.1/LICENSE.txt
updog/static/vendor/fontawesome-5.1/css/all.min.css
updog/static/vendor/fontawesome-5.1/webfonts/fa-brands-400.eot
updog/static/vendor/fontawesome-5.1/webfonts/fa-brands-400.svg
updog/static/vendor/fontawesome-5.1/webfonts/fa-brands-400.ttf
updog/static/vendor/fontawesome-5.1/webfonts/fa-brands-400.woff
updog/static/vendor/fontawesome-5.1/webfonts/fa-brands-400.woff2
updog/static/vendor/fontawesome-5.1/webfonts/fa-regular-400.eot
updog/static/vendor/fontawesome-5.1/webfonts/fa-regular-400.svg
updog/static/vendor/fontawesome-5.1/webfonts/fa-regular-400.ttf
updog-2.0.1.dist-info/LICENSE
updog-2.0.1.dist-info/METADATA
updog-2.0.1.dist-info/WHEEL
updog-2.0.1.dist-info/entry_points.txt
updog-2.0.1.dist-info/RECORD
