Metadata-Version: 2.3
Name: updog
Version: 2.0.1
Summary: Updog is a replacement for Python's SimpleHTTPServer. It allows uploading and downloading via HTTP/S, can set ad hoc SSL certificates and use HTTP basic auth.
License: MIT
Keywords: HTTP,server,SimpleHTTPServer,directory,file-sharing
Author: sc0tfree
Author-email: henry@sc0tfree.com
Requires-Python: >=3.11,<4.0
Classifier: Development Status :: 5 - Production/Stable
Classifier: Environment :: Console
Classifier: Environment :: Web Environment
Classifier: Framework :: Flask
Classifier: Intended Audience :: Developers
Classifier: Intended Audience :: System Administrators
Classifier: License :: OSI Approved :: MIT License
Classifier: Natural Language :: English
Classifier: Operating System :: MacOS
Classifier: Operating System :: Microsoft :: Windows
Classifier: Operating System :: POSIX
Classifier: Programming Language :: Python :: 3
Classifier: Programming Language :: Python :: 3.11
Classifier: Programming Language :: Python :: 3.12
Classifier: Programming Language :: Python :: 3.13
Classifier: Topic :: Communications :: File Sharing
Classifier: Topic :: Internet :: WWW/HTTP
Classifier: Topic :: Internet :: WWW/HTTP :: WSGI
Classifier: Topic :: Security
Requires-Dist: colorama (>=0.4.6,<0.5.0)
Requires-Dist: flask (>=3.0,<4.0)
Requires-Dist: flask-cors (>=6.0.1,<7.0.0)
Requires-Dist: flask-httpauth (>=4.8.0,<5.0.0)
Requires-Dist: pyopenssl (>=24.0,<25.0)
Requires-Dist: werkzeug (>=3.0,<4.0)
Project-URL: Homepage, https://github.com/sc0tfree/updog
Project-URL: Repository, https://github.com/sc0tfree/updog
